examples/__init__.py
examples/simple_metrics_otlpgrpc.py
examples/simple_metrics_stdout_default_config.py
examples/simple_trace_otlpgrpc.py
examples/simple_trace_otlpgrpc_env.py
examples/simple_trace_otlphttp_env.py
examples/simple_trace_stdout.py
examples/simple_trace_stdout_default_config.py
examples/simple_trace_stdout_env.py
examples/simple_trace_stdout_wo_sdk.py
oti/__init__.py
oti/config.py
oti/oti.py
otel_inst_py-2.2.1.dist-info/LICENSE
otel_inst_py-2.2.1.dist-info/METADATA
otel_inst_py-2.2.1.dist-info/WHEEL
otel_inst_py-2.2.1.dist-info/top_level.txt
otel_inst_py-2.2.1.dist-info/RECORD
